readthedocs_uploader/ReadTheDocsUploader.py
readthedocs_uploader/__init__.py
readthedocs_uploader/version.py
readthedocs.uploader-1.0.1.dist-info/METADATA
readthedocs.uploader-1.0.1.dist-info/WHEEL
readthedocs.uploader-1.0.1.dist-info/top_level.txt
readthedocs.uploader-1.0.1.dist-info/RECORD
