Metadata-Version: 2.1
Name: readthedocs.uploader
Version: 1.0.1
Summary: Allows you to trigger documentation from readthedocs
Home-page: UNKNOWN
License: MIT License
Keywords: python,documentation
Platform: UNKNOWN
Classifier: License :: OSI Approved :: MIT License
Classifier: Programming Language :: Python :: 3
Classifier: Programming Language :: Python :: 3.7
Requires-Dist: certifi (>=2021.5.30)
Requires-Dist: charset-normalizer (>=2.0.6)
Requires-Dist: idna (>=3.2)
Requires-Dist: requests (>=2.26.0)
Requires-Dist: urllib3 (>=1.26.6)
